flowerpower_io/__init__.py
flowerpower_io/base.py
flowerpower_io/metadata.py
flowerpower_io/helpers/datetime.py
flowerpower_io/helpers/polars.py
flowerpower_io/helpers/pyarrow.py
flowerpower_io/helpers/sql.py
flowerpower_io/loader/__init__.py
flowerpower_io/loader/csv.py
flowerpower_io/loader/deltatable.py
flowerpower_io/loader/duckdb.py
flowerpower_io/loader/json.py
flowerpower_io/loader/mqtt.py
flowerpower_io/loader/mssql.py
flowerpower_io/loader/mysql.py
flowerpower_io/loader/oracle.py
flowerpower_io/loader/parquet.py
flowerpower_io/loader/postgres.py
flowerpower_io/loader/pydala.py
flowerpower_io/loader/sqlite.py
flowerpower_io/saver/__init__.py
flowerpower_io/saver/csv.py
flowerpower_io/saver/deltatable.py
flowerpower_io/saver/duckdb.py
flowerpower_io/saver/json.py
flowerpower_io/saver/mqtt.py
flowerpower_io/saver/mssql.py
flowerpower_io/saver/mysql.py
flowerpower_io/saver/oracle.py
flowerpower_io/saver/parquet.py
flowerpower_io/saver/postgres.py
flowerpower_io/saver/pydala.py
flowerpower_io/saver/sqlite.py
flowerpower_io-0.1.6.4.dist-info/METADATA
flowerpower_io-0.1.6.4.dist-info/WHEEL
flowerpower_io-0.1.6.4.dist-info/RECORD
