Metadata-Version: 2.4
Name: flowerpower-io
Version: 0.1.6.4
Summary: Add your description here
Project-URL: homepage, https://legout.readthedocs.io/flowerpower-io
Project-URL: repository, https://github.com/legout/flowerpower-io
Author-email: legout <ligno.blades@gmail.com>
Requires-Python: >=3.11
Requires-Dist: adbc-driver-manager>=1.4.0
Requires-Dist: aiosqlite>=0.21.0
Requires-Dist: datafusion>=43.1.0
Requires-Dist: deltalake>=0.24.0
Requires-Dist: duckdb>=1.1.3
Requires-Dist: fsspec-utils>=0.1.5
Requires-Dist: msgspec>=0.19.0
Requires-Dist: orjson>=3.10.12
Requires-Dist: pandas>=2.2.3
Requires-Dist: polars>=1.15.0
Requires-Dist: pyarrow>=18.1.0
Requires-Dist: pydala2>=0.9.4.5
Requires-Dist: redis>=5.2.1
Requires-Dist: sherlock>=0.4.1
Requires-Dist: sqlalchemy>=2.0.30
Provides-Extra: legacy
Requires-Dist: polars-lts-cpu>=1.32.3; extra == 'legacy'
